sochugc/__init__.py
sochugc-1.3.0.dist-info/LICENSE
sochugc-1.3.0.dist-info/METADATA
sochugc-1.3.0.dist-info/WHEEL
sochugc-1.3.0.dist-info/top_level.txt
sochugc-1.3.0.dist-info/RECORD
