Metadata-Version: 2.1
Name: sochugc
Version: 1.3.0
Summary: API library for the cultural heritage K-Samsök (SOCH) UGC API.
Home-page: https://github.com/Abbe98/soch-ugc-py
Author: Albin Larsson
Author-email: albin.post@gmail.com
License: MIT
Download-URL: https://github.com/Abbe98/soch-ugc-py/tarball/1.3.0
Keywords: SOCH,K-Samsök,heritage,cultural,API,UGC
Platform: UNKNOWN
Classifier: License :: OSI Approved :: MIT License
Classifier: Programming Language :: Python
Classifier: Programming Language :: Python :: 3
Classifier: Programming Language :: Python :: 3.5
Classifier: Programming Language :: Python :: 3.6
Classifier: Programming Language :: Python :: 3.7
Classifier: Programming Language :: Python :: 3.8
Classifier: Programming Language :: Python :: 3 :: Only
Classifier: Intended Audience :: Developers
Classifier: Intended Audience :: Education
Requires-Python: >=3.5.0
Requires-Dist: ksamsok
Requires-Dist: requests
